hazpy/__init__.py
hazpy/__main__.py
hazpy/admin/__init__.py
hazpy/admin/tools.py
hazpy/common/__init__.py
hazpy/common/classes.py
hazpy/common/methods.py
hazpy/earthquake/__init__.py
hazpy/earthquake/classes.py
hazpy/earthquake/modules/AEBM.py
hazpy/earthquake/modules/__init__.py
hazpy/earthquake/modules/advanced_engineering_bldg_mode.py
hazpy/earthquake/modules/direct_social_losses.py
hazpy/earthquake/modules/essential_facilities.py
hazpy/earthquake/modules/general_buildings.py
hazpy/earthquake/modules/indirect_economic_loss.py
hazpy/earthquake/modules/induced_physical_damage.py
hazpy/earthquake/modules/military_installation.py
hazpy/earthquake/modules/transportation_systems.py
hazpy/earthquake/modules/user_defined_structures.py
hazpy/earthquake/modules/utility_systems.py
hazpy/flood/__init__.py
hazpy/flood/classes.py
hazpy/flood/modules/UDF.py
hazpy/flood/modules/__init__.py
hazpy/flood/modules/agriculture.py
hazpy/flood/modules/direct_social_losses.py
hazpy/flood/modules/essential_facilities.py
hazpy/flood/modules/general_building_stock.py
hazpy/flood/modules/indirect_economic_loss.py
hazpy/flood/modules/transportation_systems.py
hazpy/flood/modules/user_defined_structures.py
hazpy/flood/modules/utility_systems.py
hazpy/flood/modules/vehicles.py
hazpy/flood/modules/what_if.py
hazpy/hurricane/__init__.py
hazpy/hurricane/classes.py
hazpy/hurricane/modules/__init__.py
hazpy/hurricane/modules/direct_economic_loss.py
hazpy/hurricane/modules/direct_physical_damage.py
hazpy/hurricane/modules/direct_social_loss.py
hazpy/hurricane/modules/induced_physical_damage.py
hazpy/legacy/__init__.py
hazpy/legacy/common.py
hazpy/legacy/hazusdb.py
hazpy/legacy/report.py
hazpy/legacy/studyregion.py
hazpy/legacy/studyregiondataframe.py
hazpy/legacy/exporting/Setup_Connection.py
hazpy/legacy/exporting/__init__.py
hazpy/legacy/exporting/classes.py
hazpy/legacy/exporting/methods.py
hazpy/legacy/exporting/reports/Eq_Report_Generator.py
hazpy/legacy/exporting/reports/Fl_Report_Generator.py
hazpy-0.0.4.dist-info/LICENSE
hazpy-0.0.4.dist-info/METADATA
hazpy-0.0.4.dist-info/WHEEL
hazpy-0.0.4.dist-info/top_level.txt
hazpy-0.0.4.dist-info/RECORD
